{
    "key": "group_5b7ed8fa4ceed",
    "title": "Module - Text",
    "fields": [
        {
            "key": "field_5b7ed90135180",
            "label": "Heading",
            "name": "heading",
            "type": "text",
            "instructions": "",
            "required": 0,
            "conditional_logic": 0,
            "wrapper": {
                "width": "",
                "class": "",
                "id": ""
            },
            "default_value": "",
            "placeholder": "",
            "prepend": "",
            "append": "",
            "maxlength": ""
        },
        {
            "key": "field_5b7ed90635181",
            "label": "Copy",
            "name": "copy",
            "type": "wysiwyg",
            "instructions": "Use this field for short copy, such as an introductory paragraph (optional)",
            "required": 0,
            "conditional_logic": 0,
            "wrapper": {
                "width": "",
                "class": "",
                "id": ""
            },
            "default_value": "",
            "tabs": "visual",
            "toolbar": "basic",
            "media_upload": 0,
            "delay": 0
        },
        {
            "key": "field_5b7ed92135182",
            "label": "Additional Copy",
            "name": "additional_copy",
            "type": "wysiwyg",
            "instructions": "Use this field for longer copy, such as a list (optional)",
            "required": 0,
            "conditional_logic": 0,
            "wrapper": {
                "width": "",
                "class": "",
                "id": ""
            },
            "default_value": "",
            "tabs": "visual",
            "toolbar": "basic",
            "media_upload": 0,
            "delay": 0
        }
    ],
    "location": [
        [
            {
                "param": "post_type",
                "operator": "==",
                "value": "post"
            }
        ]
    ],
    "menu_order": 0,
    "position": "normal",
    "style": "default",
    "label_placement": "top",
    "instruction_placement": "label",
    "hide_on_screen": "",
    "active": 0,
    "description": "",
    "modified": 1535488964
}